bfcl_eval/.env.example
bfcl_eval/__init__.py
bfcl_eval/__main__.py
bfcl_eval/_llm_response_generation.py
bfcl_eval/test_case_ids_to_generate.json.example
bfcl_eval/utils.py
bfcl_eval/constants/__init__.py
bfcl_eval/constants/category_mapping.py
bfcl_eval/constants/column_headers.py
bfcl_eval/constants/default_prompts.py
bfcl_eval/constants/enums.py
bfcl_eval/constants/eval_config.py
bfcl_eval/constants/executable_backend_config.py
bfcl_eval/constants/model_config.py
bfcl_eval/constants/supported_models.py
bfcl_eval/constants/type_mappings.py
bfcl_eval/data/BFCL_v4_format_sensitivity.json
bfcl_eval/data/BFCL_v4_irrelevance.json
bfcl_eval/data/BFCL_v4_live_irrelevance.json
bfcl_eval/data/BFCL_v4_live_multiple.json
bfcl_eval/data/BFCL_v4_live_parallel.json
bfcl_eval/data/BFCL_v4_live_parallel_multiple.json
bfcl_eval/data/BFCL_v4_live_relevance.json
bfcl_eval/data/BFCL_v4_live_simple.json
bfcl_eval/data/BFCL_v4_memory.json
bfcl_eval/data/BFCL_v4_multi_turn_base.json
bfcl_eval/data/BFCL_v4_multi_turn_long_context.json
bfcl_eval/data/BFCL_v4_multi_turn_miss_func.json
bfcl_eval/data/BFCL_v4_multi_turn_miss_param.json
bfcl_eval/data/BFCL_v4_multiple.json
bfcl_eval/data/BFCL_v4_parallel.json
bfcl_eval/data/BFCL_v4_parallel_multiple.json
bfcl_eval/data/BFCL_v4_simple_java.json
bfcl_eval/data/BFCL_v4_simple_javascript.json
bfcl_eval/data/BFCL_v4_simple_python.json
bfcl_eval/data/BFCL_v4_web_search.json
bfcl_eval/data/README.md
bfcl_eval/data/memory_prereq_conversation/memory_customer.json
bfcl_eval/data/memory_prereq_conversation/memory_finance.json
bfcl_eval/data/memory_prereq_conversation/memory_healthcare.json
bfcl_eval/data/memory_prereq_conversation/memory_notetaker.json
bfcl_eval/data/memory_prereq_conversation/memory_student.json
bfcl_eval/data/multi_turn_func_doc/gorilla_file_system.json
bfcl_eval/data/multi_turn_func_doc/math_api.json
bfcl_eval/data/multi_turn_func_doc/memory_kv.json
bfcl_eval/data/multi_turn_func_doc/memory_rec_sum.json
bfcl_eval-2026.1.17.dist-info/METADATA
bfcl_eval-2026.1.17.dist-info/WHEEL
bfcl_eval-2026.1.17.dist-info/entry_points.txt
bfcl_eval-2026.1.17.dist-info/top_level.txt
bfcl_eval-2026.1.17.dist-info/RECORD
