Metadata-Version: 2.4
Name: bfcl_eval
Version: 2026.1.17
Summary: Berkeley Function Calling Leaderboard (BFCL)
Author-email: Huanzhi Mao <huanzhimao@eecs.berkeley.edu>, Shishir Patil <shishirpatil@eecs.berkeley.edu>, Sky Computing Lab <sky@cs.berkeley.edu>
License: Apache 2.0
Project-URL: Repository, https://github.com/ShishirPatil/gorilla/tree/main/berkeley-function-call-leaderboard
Requires-Python: >=3.10
Requires-Dist: requests
Requires-Dist: tqdm
Requires-Dist: numpy==1.26.4
Requires-Dist: pandas
Requires-Dist: huggingface_hub
Requires-Dist: pydantic>=2.8.2
Requires-Dist: python-dotenv>=1.0.1
Requires-Dist: tree_sitter==0.21.3
Requires-Dist: tree-sitter-java==0.21.0
Requires-Dist: tree-sitter-javascript==0.21.4
Requires-Dist: openai>=1.86.0
Requires-Dist: mistralai==1.7.0
Requires-Dist: anthropic>=0.75.0
Requires-Dist: cohere==5.18.0
Requires-Dist: typer>=0.12.5
Requires-Dist: tabulate>=0.9.0
Requires-Dist: datamodel-code-generator==0.25.7
Requires-Dist: google-genai>=1.52.0
Requires-Dist: qwen-agent
Requires-Dist: mpmath==1.3.0
Requires-Dist: tenacity>=8.5.0
Requires-Dist: writer-sdk>=2.1.0
Requires-Dist: overrides
Requires-Dist: boto3
Requires-Dist: beautifulsoup4
Requires-Dist: html2text
Requires-Dist: rank_bm25==0.2.2
Requires-Dist: google-search-results
Requires-Dist: sentence-transformers>=2.7.0
Requires-Dist: faiss-cpu==1.11.0
Requires-Dist: networkx==3.3
Requires-Dist: filelock==3.20.0
Provides-Extra: oss-eval-vllm
Requires-Dist: vllm==0.8.5; extra == "oss-eval-vllm"
Provides-Extra: oss-eval-sglang
Requires-Dist: sglang[all]; extra == "oss-eval-sglang"
Provides-Extra: wandb
Requires-Dist: wandb==0.18.5; extra == "wandb"
